aaaaa_emoji_strings.pth
emoji_strings-0.1.0.dist-info/WHEEL
emoji_strings-0.1.0.dist-info/top_level.txt
emoji_strings-0.1.0.dist-info/entry_points.txt
emoji_strings-0.1.0.dist-info/METADATA
emoji_strings-0.1.0.dist-info/LICENSE
emoji_strings/__init__.py
