Metadata-Version: 2.1
Name: emoji-strings
Version: 0.1.0
Summary: Adds support for emoji-strings in Python, which convert emoji names into actual emoji.
Author-email: Dominic Davis-Foster <dominic@davis-foster.co.uk>
License: MIT
Keywords: emoji,fstring
Home-page: https://github.com/domdfcoding/emoji-strings
Project-URL: Issue Tracker, https://github.com/domdfcoding/emoji-strings/issues
Project-URL: Source Code, https://github.com/domdfcoding/emoji-strings
Platform: Windows
Platform: macOS
Platform: Linux
Classifier: Development Status :: 4 - Beta
Classifier: Intended Audience :: Developers
Classifier: License :: OSI Approved :: MIT License
Classifier: Operating System :: OS Independent
Classifier: Programming Language :: Python
Classifier: Programming Language :: Python :: 3 :: Only
Classifier: Programming Language :: Python :: 3.6
Classifier: Programming Language :: Python :: 3.7
Classifier: Programming Language :: Python :: 3.8
Classifier: Programming Language :: Python :: 3.9
Classifier: Programming Language :: Python :: Implementation :: CPython
Classifier: Programming Language :: Python :: Implementation :: PyPy
Requires-Python: >=3.6
Requires-Dist: emoji>=1.2.0
Requires-Dist: tokenize-rt>=4.1.0
